turkishgraphy/__init__.py
turkishgraphy/cipher.py
turkishgraphy-2.0.0.dist-info/METADATA
turkishgraphy-2.0.0.dist-info/WHEEL
turkishgraphy-2.0.0.dist-info/top_level.txt
turkishgraphy-2.0.0.dist-info/RECORD
