Metadata-Version: 2.4
Name: turkishgraphy
Version: 2.0.0
Summary: Custom Turkish encryption and decryption library
Author: Cyb3rSh4d0w & dreamtech.dev
Requires-Python: >=3.8
